standardize_country/__init__.py
standardize_country-0.0.5.dist-info/LICENSE
standardize_country-0.0.5.dist-info/METADATA
standardize_country-0.0.5.dist-info/WHEEL
standardize_country-0.0.5.dist-info/top_level.txt
standardize_country-0.0.5.dist-info/RECORD
