Metadata-Version: 2.1
Name: standardize_country
Version: 0.0.5
Summary: package to standardize country names.
Home-page: https://github.com/harshil0217/standardize_country
Author: Harshil Chidura
Author-email: harshil0217@gmail.com
License: LICENSE
License-File: LICENSE
Requires-Dist: pycountry
